{"base_url":"","routes":{"salaryj_operators_index":{"tokens":[["text","\/operators\/"]],"defaults":[],"requirements":[],"hosttokens":[],"methods":["GET"],"schemes":[]},"salaryj_operators_create":{"tokens":[["text","\/operators\/new"]],"defaults":[],"requirements":[],"hosttokens":[],"methods":["GET","POST"],"schemes":[]},"salaryj_operators_update":{"tokens":[["text","\/edit"],["variable","\/","[^\/]++","id"],["text","\/operators"]],"defaults":[],"requirements":[],"hosttokens":[],"methods":["GET","PUT","PATCH"],"schemes":[]},"salaryj_operators_bulk_delete":{"tokens":[["text","\/operators\/bulk-delete"]],"defaults":[],"requirements":[],"hosttokens":[],"methods":["DELETE"],"schemes":[]},"salaryj_operators_delete":{"tokens":[["variable","\/","[^\/]++","id"],["text","\/operators"]],"defaults":[],"requirements":[],"hosttokens":[],"methods":["DELETE"],"schemes":[]},"salaryj_models_index":{"tokens":[["text","\/models\/"]],"defaults":[],"requirements":[],"hosttokens":[],"methods":["GET"],"schemes":[]},"salaryj_models_create":{"tokens":[["text","\/models\/new"]],"defaults":[],"requirements":[],"hosttokens":[],"methods":["GET","POST"],"schemes":[]},"salaryj_models_update":{"tokens":[["text","\/edit"],["variable","\/","[^\/]++","id"],["text","\/models"]],"defaults":[],"requirements":[],"hosttokens":[],"methods":["GET","PUT","PATCH"],"schemes":[]},"salaryj_models_bulk_delete":{"tokens":[["text","\/models\/bulk-delete"]],"defaults":[],"requirements":[],"hosttokens":[],"methods":["DELETE"],"schemes":[]},"salaryj_models_delete":{"tokens":[["variable","\/","[^\/]++","id"],["text","\/models"]],"defaults":[],"requirements":[],"hosttokens":[],"methods":["DELETE"],"schemes":[]},"app_operators_ext_update":{"tokens":[["text","\/operators-ext\/update"]],"defaults":[],"requirements":[],"hosttokens":[],"methods":[],"schemes":[]},"app_operators_ext_delete":{"tokens":[["text","\/operators-ext\/delete"]],"defaults":[],"requirements":[],"hosttokens":[],"methods":[],"schemes":[]},"app_models_ext_update":{"tokens":[["text","\/models-ext\/update"]],"defaults":[],"requirements":[],"hosttokens":[],"methods":[],"schemes":[]},"app_models_ext_delete":{"tokens":[["text","\/models-ext\/delete"]],"defaults":[],"requirements":[],"hosttokens":[],"methods":[],"schemes":[]},"app_operators_work_browse_totals":{"tokens":[["text","\/browse-group"],["variable","\/","[^\/]++","groupId"],["text","\/operators-work"]],"defaults":[],"requirements":[],"hosttokens":[],"methods":[],"schemes":[]}},"prefix":"","host":"localhost","port":"","scheme":"http","locale":""}